MANIFEST.in
README.md
setup.py
opclabs_pcap/__init__.py
opclabs_pcap.egg-info/PKG-INFO
opclabs_pcap.egg-info/SOURCES.txt
opclabs_pcap.egg-info/dependency_links.txt
opclabs_pcap.egg-info/not-zip-safe
opclabs_pcap.egg-info/requires.txt
opclabs_pcap.egg-info/top_level.txt
opclabs_pcap/OpcLabs.Pcap/Microsoft.NETCore.Platforms_1.1.0.txt
opclabs_pcap/OpcLabs.Pcap/Microsoft.NETCore.Targets_1.1.0.txt
opclabs_pcap/OpcLabs.Pcap/System.Runtime.CompilerServices.Unsafe_4.6.0.txt
opclabs_pcap/OpcLabs.Pcap/System.Runtime_4.3.0.txt
opclabs_pcap/OpcLabs.Pcap/gpl-3.0.txt
opclabs_pcap/OpcLabs.Pcap/lgpl-3.0.txt
opclabs_pcap/OpcLabs.Pcap/Microsoft.NETCore.Platforms_1.1.0.txt
opclabs_pcap/OpcLabs.Pcap/Microsoft.NETCore.Targets_1.1.0.txt
opclabs_pcap/OpcLabs.Pcap/System.Runtime.CompilerServices.Unsafe_4.6.0.txt
opclabs_pcap/OpcLabs.Pcap/System.Runtime_4.3.0.txt
opclabs_pcap/OpcLabs.Pcap/gpl-3.0.txt
opclabs_pcap/OpcLabs.Pcap/lgpl-3.0.txt
opclabs_pcap/OpcLabs.Pcap/net472/BoxedAppSDK.Managed.dll
opclabs_pcap/OpcLabs.Pcap/net472/Microsoft.Bcl.AsyncInterfaces.dll
opclabs_pcap/OpcLabs.Pcap/net472/Microsoft.Extensions.Caching.Abstractions.dll
opclabs_pcap/OpcLabs.Pcap/net472/Microsoft.Extensions.Caching.Memory.dll
opclabs_pcap/OpcLabs.Pcap/net472/Microsoft.Extensions.Configuration.Abstractions.dll
opclabs_pcap/OpcLabs.Pcap/net472/Microsoft.Extensions.Configuration.Binder.dll
opclabs_pcap/OpcLabs.Pcap/net472/Microsoft.Extensions.Configuration.CommandLine.dll
opclabs_pcap/OpcLabs.Pcap/net472/Microsoft.Extensions.Configuration.EnvironmentVariables.dll
opclabs_pcap/OpcLabs.Pcap/net472/Microsoft.Extensions.Configuration.FileExtensions.dll
opclabs_pcap/OpcLabs.Pcap/net472/Microsoft.Extensions.Configuration.Json.dll
opclabs_pcap/OpcLabs.Pcap/net472/Microsoft.Extensions.Configuration.UserSecrets.dll
opclabs_pcap/OpcLabs.Pcap/net472/Microsoft.Extensions.Configuration.dll
opclabs_pcap/OpcLabs.Pcap/net472/Microsoft.Extensions.DependencyInjection.Abstractions.dll
opclabs_pcap/OpcLabs.Pcap/net472/Microsoft.Extensions.DependencyInjection.dll
opclabs_pcap/OpcLabs.Pcap/net472/Microsoft.Extensions.Diagnostics.Abstractions.dll
opclabs_pcap/OpcLabs.Pcap/net472/Microsoft.Extensions.Diagnostics.dll
