Metadata-Version: 2.4
Name: opclabs_pcap
Version: 5.83.1043
Summary: Ethernet and capture file communication package.
Home-page: https://kb.opclabs.com/OpcLabs.Pcap_communication_package?python
Author: CODE Consulting and Development, s.r.o.
Author-email: sales09@opclabs.com
Keywords: QuickOPC,OPC,UA,PubSub,Ethernet,UDP,capture
License-File: opclabs_pcap/OpcLabs.Pcap/Microsoft.NETCore.Platforms_1.1.0.txt
License-File: opclabs_pcap/OpcLabs.Pcap/Microsoft.NETCore.Targets_1.1.0.txt
License-File: opclabs_pcap/OpcLabs.Pcap/System.Runtime.CompilerServices.Unsafe_4.6.0.txt
License-File: opclabs_pcap/OpcLabs.Pcap/System.Runtime_4.3.0.txt
License-File: opclabs_pcap/OpcLabs.Pcap/gpl-3.0.txt
License-File: opclabs_pcap/OpcLabs.Pcap/lgpl-3.0.txt
Requires-Dist: opclabs_quickopc
Dynamic: author
Dynamic: author-email
Dynamic: description
Dynamic: description-content-type
Dynamic: home-page
Dynamic: keywords
Dynamic: license-file
Dynamic: requires-dist
Dynamic: summary
